[
  {
    "py/object": "model.group.Group",
    "footer": "footerj8Jru7Fpimj1NQQlpzS",
    "header": "header",
    "id": null,
    "name": "namey5w"
  },
  {
    "py/object": "model.group.Group",
    "footer": "footerDkoi9",
    "header": "headerfi6ZniPslcR",
    "id": null,
    "name": "nameiACJ8fw"
  },
  {
    "py/object": "model.group.Group",
    "footer": "footer3dkCBBG7Xtykl",
    "header": "headerXT6LiSk",
    "id": null,
    "name": "namengAw"
  },
  {
    "py/object": "model.group.Group",
    "footer": "footeriRp5HwX9",
    "header": "headert0bevH5Jhf4njJ1g5K",
    "id": null,
    "name": "name34MJRzh"
  },
  {
    "py/object": "model.group.Group",
    "footer": "footerOCrPfJl72I",
    "header": "headerfX6RdnGUJ23gn",
    "id": null,
    "name": "nameev"
  }
]